azcam_imageserver/__init__.py
azcam_imageserver/imageserver.py
azcam_imageserver-23.0.dist-info/entry_points.txt
azcam_imageserver-23.0.dist-info/LICENSE
azcam_imageserver-23.0.dist-info/WHEEL
azcam_imageserver-23.0.dist-info/METADATA
azcam_imageserver-23.0.dist-info/RECORD
