Metadata-Version: 2.1
Name: azcam-imageserver
Version: 23.0
Summary: Azcam application to create a remote image server which receives images from azcamserver
Keywords: ccd,imaging,astronomy,sensors
Author: Michael Lesser
Author-email: mlesser@arizona.edu
Project-URL: Documentation, https://azcam.readthedocs.io/
Project-URL: Repository, https://github.com/mplesser/azcam-imageserver/
